pycellfit/__init__.py
pycellfit/cell.py
pycellfit/circle_fit.py
pycellfit/edge.py
pycellfit/junction.py
pycellfit/mesh.py
pycellfit/path_finder.py
pycellfit/segmentation_transform.py
pycellfit/segmentation_transform_utils.py
pycellfit/tangent_vector.py
pycellfit/utils.py
tests/__init__.py
tests/test_cell.py
tests/test_circle_fit.py
tests/test_segmentation_transform.py
tests/test_segmentation_transform_utils.py
tests/test_tangent_vector.py
tests/test_utils.py
pycellfit-0.2.3.dist-info/LICENSE
pycellfit-0.2.3.dist-info/METADATA
pycellfit-0.2.3.dist-info/WHEEL
pycellfit-0.2.3.dist-info/top_level.txt
pycellfit-0.2.3.dist-info/RECORD
